{
  "configId": 1,
  "specVersion": {
    "major": 1,
    "minor": 0
  },
  "device": {
    "deviceType": "urn:cdif-net:device:ONVIFCamera:1",
    "friendlyName": "",
    "manufacturer": "",
    "manufacturerURL": "",
    "modelDescription": "",
    "modelName": "",
    "modelNumber": "",
    "serialNumber": "",
    "UPC": "",
    "userAuth": true,
    "powerIndex": "",
    "presentationURL": "",
    "iconList": [
      {
        "mimetype": "image/png",
        "width": "",
        "height": "",
        "depth": "",
        "url": ""
      }
    ],
    "serviceList": {
      "urn:cdif-net:service:ONVIFMediaService:1": {},
      "urn:cdif-net:service:ONVIFPTZService:1": {}
    }
  }
}
